fovehicle/__init__.py
fovehicle/emotor.py
fovehicle/engine.py
fovehicle/gearbox.py
fovehicle/resistance.py
fovehicle/vehicle.py
fovehicle-0.2.0.dist-info/LICENSE.txt
fovehicle-0.2.0.dist-info/METADATA
fovehicle-0.2.0.dist-info/WHEEL
fovehicle-0.2.0.dist-info/top_level.txt
fovehicle-0.2.0.dist-info/RECORD
