Metadata-Version: 2.1
Name: fovehicle
Version: 0.2.0
Summary: Far-Out Vehicle defintion and calculation
Home-page: https://gitlab.com/far-out/fovehicle.git
Author: Jerome Douay
Author-email: jerome@far-out.biz
License: MIT
Project-URL: Documentation, https://far-out.gitlab.io/foFunction/
Project-URL: Source, https://gitlab.com/far-out/fovehicle.git
Platform: any
Classifier: Development Status :: 4 - Beta
Classifier: Programming Language :: Python
License-File: LICENSE.txt
Requires-Dist: scipy
Requires-Dist: numpy
Requires-Dist: fofunction
Requires-Dist: importlib-metadata ; python_version < "3.8"
Provides-Extra: testing
Requires-Dist: setuptools ; extra == 'testing'
Requires-Dist: pytest ; extra == 'testing'
Requires-Dist: pytest-cov ; extra == 'testing'
